wevision.cpython-37m-darwin.so
wevision-0.0.2.dist-info/METADATA
wevision-0.0.2.dist-info/WHEEL
wevision-0.0.2.dist-info/top_level.txt
wevision-0.0.2.dist-info/RECORD
