Metadata-Version: 2.1
Name: wevision
Version: 0.0.2
Summary: Python Wrapper of Wevision
Home-page: https://git.woa.com/kylofang/pywevision
Author: chaselli, kylofang, leonyliang, waynecsun
